cartai-0.0.1a1.dist-info/METADATA
cartai-0.0.1a1.dist-info/WHEEL
cartai-0.0.1a1.dist-info/entry_points.txt
cartai-0.0.1a1.dist-info/licenses/LICENSE
cartai/__init__.py
cartai/cli/commands/__init__.py
cartai/cli/commands/pr_diff.py
cartai/cli/commands/readme.py
cartai/cli/main.py
cartai/core/__init__.py
cartai/core/code_parser.py
cartai/llm_agents/__init__.py
cartai/llm_agents/documenter.py
cartai/llm_agents/graph.py
cartai/llm_agents/graph_states.py
cartai/llm_agents/templates/pr_diff.jinja
cartai/llm_agents/templates/readme.jinja
cartai/llm_agents/utils/__init__.py
cartai/llm_agents/utils/model_client_utils.py
cartai/llm_agents/utils/yaml_utils.py
cartai-0.0.1a1.dist-info/RECORD
