Metadata-Version: 2.1
Name: cartai
Version: 0.0.1a1
Summary: Agents for tracking your AI project lineage.
Project-URL: repository, https://www.github.com/ContrastoAI/cartai
Requires-Python: >=3.12
Requires-Dist: typer[all]>=0.9.0
Requires-Dist: rich>=13.7.0
Requires-Dist: litellm>=1.68.0
Requires-Dist: python-dotenv>=1.1.0
Requires-Dist: pre-commit>=4.2.0
Requires-Dist: langgraph>=0.4.3
Requires-Dist: aiofiles>=24.1.0
